jerreda-0.4.1.dist-info/METADATA
jerreda-0.4.1.dist-info/WHEEL
jerreda-0.4.1.dist-info/entry_points.txt
jerreda/__init__.py
jerreda/cli.py
jerreda-0.4.1.dist-info/RECORD
