Metadata-Version: 2.1
Name: jerreda
Version: 0.4.1
Summary: EDA
Author-Email: vhzkclq0705 <dhwns1513@gmail.com>
License: MIT
Project-URL: Homepage, https://github.com/vhzkclq0705/jerreda
Project-URL: Issues, https://github.com/vhzkclq0705/jerreda/issues
Requires-Python: >=3.10
Requires-Dist: pandas>=2.2.3
Requires-Dist: president-speech>=0.9.1
Requires-Dist: typer>=0.15.1
Requires-Dist: pytest-cov>=6.0.0
Requires-Dist: matplotlib>=3.10.0
